{"metric": "Number of active licensing deals", "synonyms": "[\n     {\n         \"text\": \"Number of active license agreements\",\n         \"score\": 0.95\n     },\n     {\n         \"text\": \"Active licensing contracts\",\n         \"score\": 0.92\n     },\n     {\n         \"text\": \"Current licensing partnerships\",\n         \"score\": 0.90\n     },\n     {\n         \"text\": \"Ongoing licensing arrangements\",\n         \"score\": 0.88\n     },\n     {\n         \"text\": \"Existing licensing deals\",\n         \"score\": 0.85\n     }\n ]"}